{
	"configurations" : 
	[
		{
			"directories" : 
			[
				{
					"build" : ".",
					"childIndexes" : 
					[
						1
					],
					"hasInstallRule" : true,
					"jsonFile" : "directory-.-Debug-f5ebdc15457944623624.json",
					"minimumCMakeVersion" : 
					{
						"string" : "3.20"
					},
					"projectIndex" : 0,
					"source" : ".",
					"targetIndexes" : 
					[
						0
					]
				},
				{
					"build" : "_deps/websocketpp-build",
					"childIndexes" : 
					[
						2
					],
					"hasInstallRule" : true,
					"jsonFile" : "directory-_deps.websocketpp-build-Debug-f216044615419f3694e2.json",
					"minimumCMakeVersion" : 
					{
						"string" : "3.10"
					},
					"parentIndex" : 0,
					"projectIndex" : 1,
					"source" : "/Users/dominikpanzarella/Desktop/crypto-bot/build/_deps/websocketpp-src"
				},
				{
					"build" : "_deps/websocketpp-build/websocketpp",
					"hasInstallRule" : true,
					"jsonFile" : "directory-_deps.websocketpp-build.websocketpp-Debug-a6abd25c501870f93425.json",
					"minimumCMakeVersion" : 
					{
						"string" : "3.10"
					},
					"parentIndex" : 1,
					"projectIndex" : 1,
					"source" : "/Users/dominikpanzarella/Desktop/crypto-bot/build/_deps/websocketpp-src/websocketpp"
				}
			],
			"name" : "Debug",
			"projects" : 
			[
				{
					"childIndexes" : 
					[
						1
					],
					"directoryIndexes" : 
					[
						0
					],
					"name" : "ArbitrageBot",
					"targetIndexes" : 
					[
						0
					]
				},
				{
					"directoryIndexes" : 
					[
						1,
						2
					],
					"name" : "websocketpp",
					"parentIndex" : 0
				}
			],
			"targets" : 
			[
				{
					"directoryIndex" : 0,
					"id" : "arbitrage_bot::@6890427a1f51a3e7e1df",
					"jsonFile" : "target-arbitrage_bot-Debug-900c27fccfa561c5e419.json",
					"name" : "arbitrage_bot",
					"projectIndex" : 0
				}
			]
		}
	],
	"kind" : "codemodel",
	"paths" : 
	{
		"build" : "/Users/dominikpanzarella/Desktop/crypto-bot/build",
		"source" : "/Users/dominikpanzarella/Desktop/crypto-bot/arbitragebot"
	},
	"version" : 
	{
		"major" : 2,
		"minor" : 8
	}
}
